<?xml version="1.0" ?>
<util.Level>
    <level>Intermediate</level>
    <exercise>
        <exercise1>Hold the lotus</exercise1>
        <exercise2>Slopes in lotus</exercise2>
        <exercise3>Lean forward</exercise3>
        <exercise4>Wide slopes</exercise4>
        <exercise5>Flexible spine</exercise5>
        <exercise6>Alternating knee to the chest</exercise6>
        <exercise7>Lying arm circle</exercise7>
        <exercise8>Head nod</exercise8>
        <exercise9>Leg and core lift</exercise9>
        <exercise10>Leg lift</exercise10>
    </exercise>
    <kalori>
        <kcal>128 kcal</kcal>
    </kalori>
    <day>
        <hari>Day 1</hari>
    </day>
    <imagePath>
        <imagePath1>/img/hold_the_lotus.png</imagePath1>
        <imagePath2>/img/slopes_in_lotus.png</imagePath2>
        <imagePath3>/img/lean_forward.png</imagePath3>
        <imagePath4>/img/wide_slopes.png</imagePath4>
        <imagePath5>/img/flexible_spine.png</imagePath5>
        <imagePath6>/img/alternating_knee_to_the_chest.png</imagePath6>
        <imagePath7>/img/lying_arm_circle.png</imagePath7>
        <imagePath8>/img/head_nod.png</imagePath8>
        <imagePath9>/img/leg_and_core_lift.png</imagePath9>
        <imagePath10>/img/leg_lift.png</imagePath10>
    </imagePath>
</util.Level>